flake8_vedro_allure/__init__.py
flake8_vedro_allure/config.py
flake8_vedro_allure/plugins.py
flake8_vedro_allure/abstract_checkers/__init__.py
flake8_vedro_allure/abstract_checkers/scenario_checker.py
flake8_vedro_allure/abstract_checkers/scenario_helper.py
flake8_vedro_allure/errors/__init__.py
flake8_vedro_allure/errors/errors.py
flake8_vedro_allure/visitors/__init__.py
flake8_vedro_allure/visitors/_visitor_with_filename.py
flake8_vedro_allure/visitors/scenario_visitor.py
flake8_vedro_allure/visitors/scenario_allure_checkers/__init__.py
flake8_vedro_allure/visitors/scenario_allure_checkers/allure_labels_checker.py
flake8_vedro_allure/visitors/scenario_allure_checkers/required_tags_checker.py
flake8_vedro_allure/visitors/scenario_allure_checkers/unique_tags_checker.py
flake8_vedro_allure-1.0.0.dist-info/LICENSE
flake8_vedro_allure-1.0.0.dist-info/METADATA
flake8_vedro_allure-1.0.0.dist-info/WHEEL
flake8_vedro_allure-1.0.0.dist-info/entry_points.txt
flake8_vedro_allure-1.0.0.dist-info/top_level.txt
flake8_vedro_allure-1.0.0.dist-info/RECORD
